afmpydes/__init__.py
afmpydes/func01.py
afmpydes/func02.py
afmpydes/func03.py
afmpydes-1.1.dist-info/METADATA
afmpydes-1.1.dist-info/WHEEL
afmpydes-1.1.dist-info/top_level.txt
afmpydes-1.1.dist-info/RECORD
