Metadata-Version: 2.1
Name: afmpydes
Version: 1.1
Summary: Calculos de Suma, Resta, Multiplicacion, Division, Exponenciacion
Home-page: https://github.com/
Author: Alberto Fernandez Maya
Author-email: afernandezm@gmail.com
License: MIT
